cloud_governance/__init__.py
cloud_governance/cloud_resource_orchestration/__init__.py
cloud_governance/cloud_resource_orchestration/aws/__init__.py
cloud_governance/cloud_resource_orchestration/aws/ec2/__init__.py
cloud_governance/cloud_resource_orchestration/aws/ec2/collect_cro_reports.py
cloud_governance/cloud_resource_orchestration/aws/ec2/cost_over_usage.py
cloud_governance/cloud_resource_orchestration/aws/ec2/monitor_cro_instances.py
cloud_governance/cloud_resource_orchestration/aws/ec2/monitor_tickets.py
cloud_governance/cloud_resource_orchestration/aws/ec2/run_cro.py
cloud_governance/cloud_resource_orchestration/aws/ec2/tag_cro_instances.py
cloud_governance/cloud_resource_orchestration/monitor/__init__.py
cloud_governance/cloud_resource_orchestration/monitor/cloud_monitor.py
cloud_governance/common/__init__.py
cloud_governance/common/clouds/__init__.py
cloud_governance/common/clouds/aws/__init__.py
cloud_governance/common/clouds/aws/cloudtrail/__init__.py
cloud_governance/common/clouds/aws/cloudtrail/cloudtrail_operations.py
cloud_governance/common/clouds/aws/cloudwatch/__init__.py
cloud_governance/common/clouds/aws/cloudwatch/cloudwatch_operations.py
cloud_governance/common/clouds/aws/cost_explorer/__init__.py
cloud_governance/common/clouds/aws/cost_explorer/cost_explorer_operations.py
cloud_governance/common/clouds/aws/dynamodb/__init__.py
cloud_governance/common/clouds/aws/dynamodb/dynamodb_operations.py
cloud_governance/common/clouds/aws/ec2/__init__.py
cloud_governance/common/clouds/aws/ec2/ec2_operations.py
cloud_governance/common/clouds/aws/iam/__init__.py
cloud_governance/common/clouds/aws/iam/iam_operations.py
cloud_governance/common/clouds/aws/price/__init__.py
cloud_governance/common/clouds/aws/price/price.py
cloud_governance/common/clouds/aws/price/resources_pricing.py
cloud_governance/common/clouds/aws/s3/__init__.py
cloud_governance/common/clouds/aws/s3/s3_operations.py
cloud_governance/common/clouds/aws/savingsplan/__init__.py
athiruma_cloud_governance-1.2.108.dist-info/LICENSE
athiruma_cloud_governance-1.2.108.dist-info/METADATA
athiruma_cloud_governance-1.2.108.dist-info/WHEEL
athiruma_cloud_governance-1.2.108.dist-info/top_level.txt
athiruma_cloud_governance-1.2.108.dist-info/RECORD
